Workbook

Sheet Пассивки Странника
A1: № | B1: Категория | C1: Редкость | D1: Название | E1: Эффект | F1: Сила влияния | G1: Вес (авто) | H1: Семейство | I1: Стек
A2: 1 | B2: Артефакты | C2: Обычная | D2: Знакомый мастер | E2: Цена покупки артефактов золотом −3% | F2: 1 — мелкая | G2: =IFERROR(ROUND(INDEX(Настройки!$B$3:$B$9,MATCH($C2,Настройки!$A$3:$A$9,0))*INDEX(Настройки!$E$3:$E$7,MATCH($F2,Настройки!$D$3:$D$7,0)),0),"") -> 125 | H2: Артефакты: золото | I2: не стакается внутри семейства
A3: 2 | B3: Дух | C3: Обычная | D3: Гулкий отзвук | E3: 5% шанс двойного духа с босса биома | F3: 1 — мелкая | G3: =IFERROR(ROUND(INDEX(Настройки!$B$3:$B$9,MATCH($C3,Настройки!$A$3:$A$9,0))*INDEX(Настройки!$E$3:$E$7,MATCH($F3,Настройки!$D$3:$D$7,0)),0),"") -> 125 | H3: Дух: боссы | I3: не стакается внутри семейства
A4: 3 | B4: Дух | C4: Обычная | D4: Жадное ухо | E4: 5% шанс двойного духа с обычного врага | F4: 1 — мелкая | G4: =IFERROR(ROUND(INDEX(Настройки!$B$3:$B$9,MATCH($C4,Настройки!$A$3:$A$9,0))*INDEX(Настройки!$E$3:$E$7,MATCH($F4,Настройки!$D$3:$D$7,0)),0),"") -> 125 | H4: Дух: обычные | I4: не стакается внутри семейства
A5: 4 | B5: Дух | C5: Уникальная | D5: Пыль побед | E5: Дух после закрытия биома +5% | F5: 1 — мелкая | G5: =IFERROR(ROUND(INDEX(Настройки!$B$3:$B$9,MATCH($C5,Настройки!$A$3:$A$9,0))*INDEX(Настройки!$E$3:$E$7,MATCH($F5,Настройки!$D$3:$D$7,0)),0),"") -> 73 | H5: Дух: закрытие биома | I5: не стакается внутри семейства
A6: 5 | B6: Золото | C6: Обычная | D6: Дорожный сбор | E6: Золото за закрытие биома +5% | F6: 1 — мелкая | G6: =IFERROR(ROUND(INDEX(Настройки!$B$3:$B$9,MATCH($C6,Настройки!$A$3:$A$9,0))*INDEX(Настройки!$E$3:$E$7,MATCH($F6,Настройки!$D$3:$D$7,0)),0),"") -> 125 | H6: Золото: закрытие биома | I6: не стакается внутри семейства
A7: 6 | B7: Золото | C7: Обычная | D7: Звонкая мелочь | E7: 1% шанс двойного золота с элиты | F7: 1 — мелкая | G7: =IFERROR(ROUND(INDEX(Настройки!$B$3:$B$9,MATCH($C7,Настройки!$A$3:$A$9,0))*INDEX(Настройки!$E$3:$E$7,MATCH($F7,Настройки!$D$3:$D$7,0)),0),"") -> 125 | H7: Доп. Дроп Золото | I7: не стакается внутри семейства
A8: 7 | B8: Золото | C8: Обычная | D8: Первая жила | E8: 0.5% шанс двойного золота с обычного врага | F8: 1 — мелкая | G8: =IFERROR(ROUND(INDEX(Настройки!$B$3:$B$9,MATCH($C8,Настройки!$A$3:$A$9,0))*INDEX(Настройки!$E$3:$E$7,MATCH($F8,Настройки!$D$3:$D$7,0)),0),"") -> 125 | H8: Доп. Дроп Золото | I8: не стакается внутри семейства
A9: 8 | B9: Календарь | C9: Обычная | D9: Гостеприимство | E9: Ежедневная награда календаря +10% валюты | F9: 1 — мелкая | G9: =IFERROR(ROUND(INDEX(Настройки!$B$3:$B$9,MATCH($C9,Настройки!$A$3:$A$9,0))*INDEX(Настройки!$E$3:$E$7,MATCH($F9,Настройки!$D$3:$D$7,0)),0),"") -> 125 | H9: Календарь | I9: не стакается внутри семейства
A10: 9 | B10: Кланы | C10: Древняя | D10: Доброе слово | E10: Личные очки Кланового босса +1% | F10: 5 — меняет билд | G10: =IFERROR(ROUND(INDEX(Настройки!$B$3:$B$9,MATCH($C10,Настройки!$A$3:$A$9,0))*INDEX(Настройки!$E$3:$E$7,MATCH($F10,Настройки!$D$3:$D$7,0)),0),"") -> 23 | H10: Очки: КБ | I10: не стакается внутри семейства
A11: 10 | B11: Кланы | C11: Обычная | D11: Малый вклад | E11: Вклад в резервуар клана +1% | F11: 3 — сильная | G11: =IFERROR(ROUND(INDEX(Настройки!$B$3:$B$9,MATCH($C11,Настройки!$A$3:$A$9,0))*INDEX(Настройки!$E$3:$E$7,MATCH($F11,Настройки!$D$3:$D$7,0)),0),"") -> 100 | H11: Кланы: резервуар | I11: не стакается внутри семейства
A12: 11 | B12: Контракты | C12: Обычная | D12: Малый оброк | E12: Награда золотом из контрактов +3% | F12: 1 — мелкая | G12: =IFERROR(ROUND(INDEX(Настройки!$B$3:$B$9,MATCH($C12,Настройки!$A$3:$A$9,0))*INDEX(Настройки!$E$3:$E$7,MATCH($F12,Настройки!$D$3:$D$7,0)),0),"") -> 125 | H12: Контракты: золото | I12: не стакается внутри семейства
A13: 12 | B13: Магазин | C13: Обычная | D13: Приметливый глаз | E13: 5% шанс, что в обновлении магазина будет товар редкой+ редкости | F13: 1 — мелкая | G13: =IFERROR(ROUND(INDEX(Настройки!$B$3:$B$9,MATCH($C13,Настройки!$A$3:$A$9,0))*INDEX(Настройки!$E$3:$E$7,MATCH($F13,Настройки!$D$3:$D$7,0)),0),"") -> 125 | H13: Магазин: ассортимент | I13: не стакается внутри семейства
... A147: 210 | B147: Руны | C147: Вневременная | D147: Рунный ливень | E147: 10% шанс дополнительной руны за убийство рунного босса | F147: 5 — меняет билд | G147: =IFERROR(ROUND(INDEX(Настройки!$B$3:$B$9,MATCH($C147,Настройки!$A$3:$A$9,0))*INDEX(Настройки!$E$3:$E$7,MATCH($F147,Настройки!$D$3:$D$7,0)),0),"") -> 13 | H147: Руны: доп. руна | I147: не стакается внутри семейства

Sheet Настройки
A1: НАСТРОЙКИ ВЕСОВ — меняй только эту страницу, веса пересчитаются сами
A2: Редкость | B2: Базовый вес | D2: Сила влияния | E2: Множитель
A3: Обычная | B3: 100 | D3: 1 — мелкая | E3: 1.25
A4: Редкая | B4: 75 | D4: 2 — заметная | E4: 1.1
A5: Уникальная | B5: 58 | D5: 3 — сильная | E5: 1
A6: Эпическая | B6: 45 | D6: 4 — очень сильная | E6: 0.85
A7: Древняя | B7: 33 | D7: 5 — меняет билд | E7: 0.7
A8: Первородная | B8: 25
A9: Вневременная | B9: 18
A12: Вес = Базовый вес редкости × Множитель силы влияния (округление до целого).
A13: Чем сильнее перк влияет на билд — тем меньше множитель и тем реже он выпадает внутри своей редкости.

Sheet Сводка
A1: СВОДКА ПО ПУЛУ (считается автоматически)
A3: Редкость | B3: Штук | C3: Сумма весов | D3: Доля пула
A4: Обычная | B4: =COUNTIF('Пассивки Странника'!$C:$C,$A4) -> 28 | C4: =SUMIF('Пассивки Странника'!$C:$C,$A4,'Пассивки Странника'!$G:$G) -> 3235 | D4: =IFERROR(B4/$B$11,0) -> 0.19178082
A5: Редкая | B5: =COUNTIF('Пассивки Странника'!$C:$C,$A5) -> 31 | C5: =SUMIF('Пассивки Странника'!$C:$C,$A5,'Пассивки Странника'!$G:$G) -> 2393 | D5: =IFERROR(B5/$B$11,0) -> 0.21232877
A6: Уникальная | B6: =COUNTIF('Пассивки Странника'!$C:$C,$A6) -> 31 | C6: =SUMIF('Пассивки Странника'!$C:$C,$A6,'Пассивки Странника'!$G:$G) -> 1711 | D6: =IFERROR(B6/$B$11,0) -> 0.21232877
A7: Эпическая | B7: =COUNTIF('Пассивки Странника'!$C:$C,$A7) -> 21 | C7: =SUMIF('Пассивки Странника'!$C:$C,$A7,'Пассивки Странника'!$G:$G) -> 927 | D7: =IFERROR(B7/$B$11,0) -> 0.14383562
A8: Древняя | B8: =COUNTIF('Пассивки Странника'!$C:$C,$A8) -> 14 | C8: =SUMIF('Пассивки Странника'!$C:$C,$A8,'Пассивки Странника'!$G:$G) -> 395 | D8: =IFERROR(B8/$B$11,0) -> 0.095890411
A9: Первородная | B9: =COUNTIF('Пассивки Странника'!$C:$C,$A9) -> 13 | C9: =SUMIF('Пассивки Странника'!$C:$C,$A9,'Пассивки Странника'!$G:$G) -> 298 | D9: =IFERROR(B9/$B$11,0) -> 0.089041096
A10: Вневременная | B10: =COUNTIF('Пассивки Странника'!$C:$C,$A10) -> 8 | C10: =SUMIF('Пассивки Странника'!$C:$C,$A10,'Пассивки Странника'!$G:$G) -> 115 | D10: =IFERROR(B10/$B$11,0) -> 0.054794521
A11: Всего | B11: =SUM(B4:B10) -> 146
A13: Вероятность конкретного перка внутри редкости = его вес ÷ сумма весов этой редкости.
A14: Веса самих редкостей при ролле тройки задаются отдельно по номеру перехода цикла.

Sheet Правила пула
A1: ПАССИВКИ СТРАННИКА — версия 5 (пирамида собрана). Числа стартовые, под прогоны.
A3: Пирамида: обычных 50 → редких 46 → уникальных 43 → эпических 29 → древних 19 → первородных 13 → вневременных 10. Всего 210.
A5: КАК ПОЛЬЗОВАТЬСЯ: редкость и силу влияния меняй выпадающими списками (колонки C и F) — вес пересчитается сам,
A6: цвет строки сменится, сводка обновится. Базовые веса и множители — на листе «Настройки».
A8: 1. Пять пассивок за игру: по одной на каждом переходе цикла. Выбор 1 из 3, перерол тройки — за Энериум.
A9: 2. Сброс билда за Энериум — не чаще раза в неделю Элемента (монетизация).
A10: 3. Ролл: сначала редкость (веса редкостей по номеру перехода), затем перк внутри редкости по весу.
A11: 4. Семейства: перки одного семейства не стакаются — работает сильнейший. Разные семейства складываются.
A12: 5. Проценты применяются к базе, дробная часть разыгрывается от серверного сида; плоские добавки — после процентных; минимум 1 везде.
A13: 6. Сторожа: кап убийств РБ не поднимается; «ноль»-законы не обходятся; отсечка недели, «всё или ничего» контрактов и Эло неприкосновенны.
A14: 7. Перки на очки рейтингов (Эхо, Событие, КБ, контракты) множат заработанные очки, но не дают очков за неигровые действия.
